evaler/__init__.py
evaler/_version.py
evaler/inverse_eval.py
evaler/inverse_evaler.py
evaler/mne_simulation.py
evaler/plotting_tools.py
evaler/settings.py
evaler/source_space_tools.py
evaler-0.0.2.dist-info/METADATA
evaler-0.0.2.dist-info/WHEEL
evaler-0.0.2.dist-info/top_level.txt
evaler-0.0.2.dist-info/RECORD
